stix2xspec/__init__.py
stix2xspec/__main__.py
stix2xspec/data/__init__.py
stix2xspec/data/adg_table.json
stix2xspec/data/solo_L1A_stix-sci-spectrogram-2207238956_20220723T122007-20220723T182511_079258_V01.fits
stix2xspec/data/solo_L1A_stix-sci-xray-l1-2207235029_20220723T113947-20220723T122747_079205_V01.fits
stix2xspec/data/stx_spectrum_20220723_122031.fits
stix2xspec/data/stx_srm_full.fits
stix2xspec/livetime.py
stix2xspec/spectrogram.py
stix2xspec/spectrogram_utils.py
stix2xspec/stix2xspec.py
stix2xspec/triggergram.py
stix2xspec/write_spectrum2fits.py
stix2xspec/xspec_utils.py
stix2xspec-0.1.0.dist-info/entry_points.txt
stix2xspec-0.1.0.dist-info/LICENSE
stix2xspec-0.1.0.dist-info/WHEEL
stix2xspec-0.1.0.dist-info/METADATA
stix2xspec-0.1.0.dist-info/RECORD
